{
  "version": "1.2.0",
  "items": [
    {
      "id": "malt_pils_weyermann",
      "name": "Pilsner Malt",
      "category": "malt",
      "supplier": "Weyermann",
      "unit": "kg",
      "color": 3.5,
      "potential": 1.038,
      "yield": 81,
      "maltType": "base",
      "origin": "Germany"
    },
    {
      "id": "malt_pils_bestmalz",
      "name": "Pilsner Malt",
      "category": "malt",
      "supplier": "BestMalz",
      "unit": "kg",
      "color": 3.0,
      "potential": 1.038,
      "yield": 82,
      "maltType": "base",
      "origin": "Germany"
    },
    {
      "id": "malt_pils_avangard",
      "name": "Pilsner Malt",
      "category": "malt",
      "supplier": "Avangard",
      "unit": "kg",
      "color": 3.5,
      "potential": 1.037,
      "yield": 80,
      "maltType": "base",
      "origin": "Germany"
    },
    {
      "id": "malt_pils_ireks",
      "name": "Pilsner Malt",
      "category": "malt",
      "supplier": "IREKS",
      "unit": "kg",
      "color": 3.2,
      "potential": 1.037,
      "yield": 80,
      "maltType": "base",
      "origin": "Germany"
    },
    {
      "id": "malt_pils_castle",
      "name": "Pilsner Malt",
      "category": "malt",
      "supplier": "Castle Malting",
      "unit": "kg",
      "color": 3.5,
      "potential": 1.037,
      "yield": 80,
      "maltType": "base",
      "origin": "Belgium"
    },
    {
      "id": "malt_pils_dingemans",
      "name": "Pilsner Malt",
      "category": "malt",
      "supplier": "Dingemans",
      "unit": "kg",
      "color": 3.0,
      "potential": 1.037,
      "yield": 80,
      "maltType": "base",
      "origin": "Belgium"
    },
    {
      "id": "malt_pils_simpsons",
      "name": "Pilsner Malt",
      "category": "malt",
      "supplier": "Simpsons",
      "unit": "kg",
      "color": 3.2,
      "potential": 1.037,
      "yield": 80,
      "maltType": "base",
      "origin": "UK"
    },
    {
      "id": "malt_pils_crisp",
      "name": "Pilsner Malt",
      "category": "malt",
      "supplier": "Crisp",
      "unit": "kg",
      "color": 3.0,
      "potential": 1.037,
      "yield": 80,
      "maltType": "base",
      "origin": "UK"
    },
    {
      "id": "malt_munich_weyermann",
      "name": "Munich Malt Type I",
      "category": "malt",
      "supplier": "Weyermann",
      "unit": "kg",
      "color": 14,
      "potential": 1.037,
      "yield": 80,
      "maltType": "base",
      "origin": "Germany"
    },
    {
      "id": "malt_munich_bestmalz",
      "name": "Munich Malt",
      "category": "malt",
      "supplier": "BestMalz",
      "unit": "kg",
      "color": 15,
      "potential": 1.037,
      "yield": 80,
      "maltType": "base",
      "origin": "Germany"
    },
    {
      "id": "malt_munich_avangard",
      "name": "Munich Malt",
      "category": "malt",
      "supplier": "Avangard",
      "unit": "kg",
      "color": 15,
      "potential": 1.036,
      "yield": 78,
      "maltType": "base",
      "origin": "Germany"
    },
    {
      "id": "malt_vienna_weyermann",
      "name": "Vienna Malt",
      "category": "malt",
      "supplier": "Weyermann",
      "unit": "kg",
      "color": 7,
      "potential": 1.037,
      "yield": 80,
      "maltType": "base",
      "origin": "Germany"
    },
    {
      "id": "malt_vienna_bestmalz",
      "name": "Vienna Malt",
      "category": "malt",
      "supplier": "BestMalz",
      "unit": "kg",
      "color": 7,
      "potential": 1.037,
      "yield": 80,
      "maltType": "base",
      "origin": "Germany"
    },
    {
      "id": "malt_caramunich_weyermann",
      "name": "CaraMunich I",
      "category": "malt",
      "supplier": "Weyermann",
      "unit": "kg",
      "color": 90,
      "potential": 1.034,
      "yield": 74,
      "maltType": "caramel",
      "origin": "Germany"
    },
    {
      "id": "malt_carapils_weyermann",
      "name": "CaraPils / CaraFoam",
      "category": "malt",
      "supplier": "Weyermann",
      "unit": "kg",
      "color": 4,
      "potential": 1.033,
      "yield": 72,
      "maltType": "caramel",
      "origin": "Germany"
    },
    {
      "id": "malt_caravienne_weyermann",
      "name": "CaraVienne",
      "category": "malt",
      "supplier": "Weyermann",
      "unit": "kg",
      "color": 25,
      "potential": 1.034,
      "yield": 74,
      "maltType": "caramel",
      "origin": "Germany"
    },
    {
      "id": "malt_carafa_weyermann",
      "name": "Carafa Special II",
      "category": "malt",
      "supplier": "Weyermann",
      "unit": "kg",
      "color": 1100,
      "potential": 1.032,
      "yield": 70,
      "maltType": "roasted",
      "origin": "Germany"
    },
    {
      "id": "malt_wheat_weyermann",
      "name": "Wheat Malt",
      "category": "malt",
      "supplier": "Weyermann",
      "unit": "kg",
      "color": 4,
      "potential": 1.038,
      "yield": 84,
      "maltType": "base",
      "origin": "Germany"
    },
    {
      "id": "malt_wheat_bestmalz",
      "name": "Wheat Malt",
      "category": "malt",
      "supplier": "BestMalz",
      "unit": "kg",
      "color": 4,
      "potential": 1.038,
      "yield": 83,
      "maltType": "base",
      "origin": "Germany"
    },
    {
      "id": "malt_maris_simpsons",
      "name": "Maris Otter",
      "category": "malt",
      "supplier": "Simpsons",
      "unit": "kg",
      "color": 5,
      "potential": 1.038,
      "yield": 82,
      "maltType": "base",
      "origin": "UK"
    },
    {
      "id": "malt_maris_crisp",
      "name": "Maris Otter",
      "category": "malt",
      "supplier": "Crisp",
      "unit": "kg",
      "color": 5,
      "potential": 1.038,
      "yield": 82,
      "maltType": "base",
      "origin": "UK"
    },
    {
      "id": "malt_crystal_dingemans",
      "name": "Crystal Malt",
      "category": "malt",
      "supplier": "Dingemans",
      "unit": "kg",
      "color": 60,
      "potential": 1.034,
      "yield": 74,
      "maltType": "caramel",
      "origin": "Belgium"
    },
    {
      "id": "malt_biscuit_dingemans",
      "name": "Biscuit Malt",
      "category": "malt",
      "supplier": "Dingemans",
      "unit": "kg",
      "color": 45,
      "potential": 1.035,
      "yield": 76,
      "maltType": "specialty",
      "origin": "Belgium"
    },
    {
      "id": "malt_aromatic_dingemans",
      "name": "Aromatic Malt",
      "category": "malt",
      "supplier": "Dingemans",
      "unit": "kg",
      "color": 50,
      "potential": 1.036,
      "yield": 78,
      "maltType": "specialty",
      "origin": "Belgium"
    },
    {
      "id": "malt_pilsner_boortmalt",
      "name": "Pilsner Malt",
      "category": "malt",
      "supplier": "Boortmalt",
      "unit": "kg",
      "color": 3.5,
      "potential": 1.037,
      "yield": 80,
      "maltType": "base",
      "origin": "Belgium"
    },
    {
      "id": "malt_pale_ale_boortmalt",
      "name": "Pale Ale Malt",
      "category": "malt",
      "supplier": "Boortmalt",
      "unit": "kg",
      "color": 7,
      "potential": 1.037,
      "yield": 80,
      "maltType": "base",
      "origin": "Belgium"
    },
    {
      "id": "malt_vienna_boortmalt",
      "name": "Vienna Malt",
      "category": "malt",
      "supplier": "Boortmalt",
      "unit": "kg",
      "color": 8,
      "potential": 1.036,
      "yield": 78,
      "maltType": "base",
      "origin": "Belgium"
    },
    {
      "id": "malt_munich_boortmalt",
      "name": "Munich Malt",
      "category": "malt",
      "supplier": "Boortmalt",
      "unit": "kg",
      "color": 15,
      "potential": 1.036,
      "yield": 78,
      "maltType": "base",
      "origin": "Belgium"
    },
    {
      "id": "malt_wheat_boortmalt",
      "name": "Wheat Malt",
      "category": "malt",
      "supplier": "Boortmalt",
      "unit": "kg",
      "color": 4,
      "potential": 1.037,
      "yield": 82,
      "maltType": "base",
      "origin": "Belgium"
    },
    {
      "id": "malt_crystal60_boortmalt",
      "name": "Crystal 60",
      "category": "malt",
      "supplier": "Boortmalt",
      "unit": "kg",
      "color": 60,
      "potential": 1.034,
      "yield": 74,
      "maltType": "caramel",
      "origin": "Belgium"
    },
    {
      "id": "malt_pilsner_viking",
      "name": "Pilsner Malt",
      "category": "malt",
      "supplier": "Viking Malt",
      "unit": "kg",
      "color": 3.5,
      "potential": 1.037,
      "yield": 81,
      "maltType": "base",
      "origin": "Finland"
    },
    {
      "id": "malt_pale_ale_viking",
      "name": "Pale Ale Malt",
      "category": "malt",
      "supplier": "Viking Malt",
      "unit": "kg",
      "color": 6,
      "potential": 1.037,
      "yield": 80,
      "maltType": "base",
      "origin": "Finland"
    },
    {
      "id": "malt_vienna_viking",
      "name": "Vienna Malt",
      "category": "malt",
      "supplier": "Viking Malt",
      "unit": "kg",
      "color": 8,
      "potential": 1.036,
      "yield": 79,
      "maltType": "base",
      "origin": "Finland"
    },
    {
      "id": "malt_munich_viking",
      "name": "Munich Malt",
      "category": "malt",
      "supplier": "Viking Malt",
      "unit": "kg",
      "color": 17,
      "potential": 1.036,
      "yield": 78,
      "maltType": "base",
      "origin": "Finland"
    },
    {
      "id": "malt_wheat_viking",
      "name": "Wheat Malt",
      "category": "malt",
      "supplier": "Viking Malt",
      "unit": "kg",
      "color": 4,
      "potential": 1.038,
      "yield": 83,
      "maltType": "base",
      "origin": "Finland"
    },
    {
      "id": "malt_crystal60_viking",
      "name": "Crystal 60",
      "category": "malt",
      "supplier": "Viking Malt",
      "unit": "kg",
      "color": 60,
      "potential": 1.034,
      "yield": 74,
      "maltType": "caramel",
      "origin": "Finland"
    },
    {
      "id": "malt_pilsner_swaen",
      "name": "Pilsner Malt",
      "category": "malt",
      "supplier": "Swaen",
      "unit": "kg",
      "color": 3.5,
      "potential": 1.037,
      "yield": 81,
      "maltType": "base",
      "origin": "Netherlands"
    },
    {
      "id": "malt_pale_ale_swaen",
      "name": "Pale Ale Malt",
      "category": "malt",
      "supplier": "Swaen",
      "unit": "kg",
      "color": 7,
      "potential": 1.037,
      "yield": 80,
      "maltType": "base",
      "origin": "Netherlands"
    },
    {
      "id": "malt_vienna_swaen",
      "name": "Vienna Malt",
      "category": "malt",
      "supplier": "Swaen",
      "unit": "kg",
      "color": 8,
      "potential": 1.036,
      "yield": 79,
      "maltType": "base",
      "origin": "Netherlands"
    },
    {
      "id": "malt_munich_swaen",
      "name": "Munich Malt",
      "category": "malt",
      "supplier": "Swaen",
      "unit": "kg",
      "color": 18,
      "potential": 1.036,
      "yield": 78,
      "maltType": "base",
      "origin": "Netherlands"
    },
    {
      "id": "malt_wheat_swaen",
      "name": "Wheat Malt",
      "category": "malt",
      "supplier": "Swaen",
      "unit": "kg",
      "color": 4,
      "potential": 1.037,
      "yield": 82,
      "maltType": "base",
      "origin": "Netherlands"
    },
    {
      "id": "malt_crystal60_swaen",
      "name": "Crystal 60",
      "category": "malt",
      "supplier": "Swaen",
      "unit": "kg",
      "color": 60,
      "potential": 1.034,
      "yield": 74,
      "maltType": "caramel",
      "origin": "Netherlands"
    },
    {
      "id": "malt_pilsner_soufflet",
      "name": "Pilsner Malt",
      "category": "malt",
      "supplier": "Soufflet",
      "unit": "kg",
      "color": 3.5,
      "potential": 1.037,
      "yield": 80,
      "maltType": "base",
      "origin": "France"
    },
    {
      "id": "malt_pale_ale_soufflet",
      "name": "Pale Ale Malt",
      "category": "malt",
      "supplier": "Soufflet",
      "unit": "kg",
      "color": 7,
      "potential": 1.037,
      "yield": 80,
      "maltType": "base",
      "origin": "France"
    },
    {
      "id": "malt_vienna_soufflet",
      "name": "Vienna Malt",
      "category": "malt",
      "supplier": "Soufflet",
      "unit": "kg",
      "color": 8,
      "potential": 1.036,
      "yield": 78,
      "maltType": "base",
      "origin": "France"
    },
    {
      "id": "malt_munich_soufflet",
      "name": "Munich Malt",
      "category": "malt",
      "supplier": "Soufflet",
      "unit": "kg",
      "color": 16,
      "potential": 1.036,
      "yield": 78,
      "maltType": "base",
      "origin": "France"
    },
    {
      "id": "malt_wheat_soufflet",
      "name": "Wheat Malt",
      "category": "malt",
      "supplier": "Soufflet",
      "unit": "kg",
      "color": 4,
      "potential": 1.037,
      "yield": 82,
      "maltType": "base",
      "origin": "France"
    },
    {
      "id": "malt_crystal60_soufflet",
      "name": "Crystal 60",
      "category": "malt",
      "supplier": "Soufflet",
      "unit": "kg",
      "color": 60,
      "potential": 1.034,
      "yield": 74,
      "maltType": "caramel",
      "origin": "France"
    },
    {
      "id": "hop_saaz_bohemia",
      "name": "Saaz",
      "category": "hops",
      "supplier": "Bohemia Hop",
      "unit": "kg",
      "alphaAcid": 3.5,
      "betaAcid": 3.5,
      "form": "pellet",
      "purpose": "aroma",
      "origin": "Czech Republic"
    },
    {
      "id": "hop_saaz_zatec",
      "name": "Saaz",
      "category": "hops",
      "supplier": "Žatec Hop Union",
      "unit": "kg",
      "alphaAcid": 3.5,
      "betaAcid": 3.5,
      "form": "pellet",
      "purpose": "aroma",
      "origin": "Czech Republic"
    },
    {
      "id": "hop_hallertauer_hopsteiner",
      "name": "Hallertauer Mittelfrüh",
      "category": "hops",
      "supplier": "Hopsteiner",
      "unit": "kg",
      "alphaAcid": 4.0,
      "betaAcid": 4.5,
      "form": "pellet",
      "purpose": "aroma",
      "origin": "Germany"
    },
    {
      "id": "hop_hallertauer_barthhaas",
      "name": "Hallertauer Mittelfrüh",
      "category": "hops",
      "supplier": "BarthHaas",
      "unit": "kg",
      "alphaAcid": 4.0,
      "betaAcid": 4.5,
      "form": "pellet",
      "purpose": "aroma",
      "origin": "Germany"
    },
    {
      "id": "hop_tettnang_hopsteiner",
      "name": "Tettnang",
      "category": "hops",
      "supplier": "Hopsteiner",
      "unit": "kg",
      "alphaAcid": 4.5,
      "betaAcid": 4.0,
      "form": "pellet",
      "purpose": "aroma",
      "origin": "Germany"
    },
    {
      "id": "hop_tettnang_barthhaas",
      "name": "Tettnang",
      "category": "hops",
      "supplier": "BarthHaas",
      "unit": "kg",
      "alphaAcid": 4.5,
      "betaAcid": 4.0,
      "form": "pellet",
      "purpose": "aroma",
      "origin": "Germany"
    },
    {
      "id": "hop_spalt_hopsteiner",
      "name": "Spalt",
      "category": "hops",
      "supplier": "Hopsteiner",
      "unit": "kg",
      "alphaAcid": 4.5,
      "betaAcid": 4.0,
      "form": "pellet",
      "purpose": "aroma",
      "origin": "Germany"
    },
    {
      "id": "hop_perle_hopsteiner",
      "name": "Perle",
      "category": "hops",
      "supplier": "Hopsteiner",
      "unit": "kg",
      "alphaAcid": 7.5,
      "betaAcid": 4.5,
      "form": "pellet",
      "purpose": "dual",
      "origin": "Germany"
    },
    {
      "id": "hop_hersbrucker_hopsteiner",
      "name": "Hersbrucker",
      "category": "hops",
      "supplier": "Hopsteiner",
      "unit": "kg",
      "alphaAcid": 3.5,
      "betaAcid": 5.0,
      "form": "pellet",
      "purpose": "aroma",
      "origin": "Germany"
    },
    {
      "id": "hop_premiant_bohemia",
      "name": "Premiant",
      "category": "hops",
      "supplier": "Bohemia Hop",
      "unit": "kg",
      "alphaAcid": 9.0,
      "betaAcid": 4.5,
      "form": "pellet",
      "purpose": "bittering",
      "origin": "Czech Republic"
    },
    {
      "id": "hop_sladek_bohemia",
      "name": "Sládek",
      "category": "hops",
      "supplier": "Bohemia Hop",
      "unit": "kg",
      "alphaAcid": 6.5,
      "betaAcid": 4.5,
      "form": "pellet",
      "purpose": "dual",
      "origin": "Czech Republic"
    },
    {
      "id": "hop_magnum_barthhaas",
      "name": "Magnum",
      "category": "hops",
      "supplier": "BarthHaas",
      "unit": "kg",
      "alphaAcid": 13.0,
      "betaAcid": 5.5,
      "form": "pellet",
      "purpose": "bittering",
      "origin": "Germany"
    },
    {
      "id": "hop_cascade_barthhaas",
      "name": "Cascade",
      "category": "hops",
      "supplier": "BarthHaas",
      "unit": "kg",
      "alphaAcid": 6.0,
      "betaAcid": 6.0,
      "form": "pellet",
      "purpose": "aroma",
      "origin": "USA"
    },
    {
      "id": "hop_centennial_barthhaas",
      "name": "Centennial",
      "category": "hops",
      "supplier": "BarthHaas",
      "unit": "kg",
      "alphaAcid": 10.0,
      "betaAcid": 4.0,
      "form": "pellet",
      "purpose": "dual",
      "origin": "USA"
    },
    {
      "id": "hop_citra_barthhaas",
      "name": "Citra",
      "category": "hops",
      "supplier": "BarthHaas",
      "unit": "kg",
      "alphaAcid": 12.0,
      "betaAcid": 4.0,
      "form": "pellet",
      "purpose": "aroma",
      "origin": "USA"
    },
    {
      "id": "hop_mosaic_barthhaas",
      "name": "Mosaic",
      "category": "hops",
      "supplier": "BarthHaas",
      "unit": "kg",
      "alphaAcid": 12.5,
      "betaAcid": 3.5,
      "form": "pellet",
      "purpose": "aroma",
      "origin": "USA"
    },
    {
      "id": "hop_simcoe_barthhaas",
      "name": "Simcoe",
      "category": "hops",
      "supplier": "BarthHaas",
      "unit": "kg",
      "alphaAcid": 13.0,
      "betaAcid": 4.5,
      "form": "pellet",
      "purpose": "dual",
      "origin": "USA"
    },
    {
      "id": "yeast_lager_fermentis",
      "name": "SafLager W-34/70",
      "category": "yeast",
      "supplier": "Fermentis",
      "unit": "pack",
      "attenuation": "80-84%",
      "tempRange": "9-15°C",
      "flocculation": "high",
      "yeastType": "lager"
    },
    {
      "id": "yeast_lager_s23_fermentis",
      "name": "SafLager S-23",
      "category": "yeast",
      "supplier": "Fermentis",
      "unit": "pack",
      "attenuation": "80-84%",
      "tempRange": "9-15°C",
      "flocculation": "high",
      "yeastType": "lager"
    },
    {
      "id": "yeast_lager_lallemand",
      "name": "LalBrew Diamond",
      "category": "yeast",
      "supplier": "Lallemand",
      "unit": "pack",
      "attenuation": "77-83%",
      "tempRange": "10-15°C",
      "flocculation": "high",
      "yeastType": "lager"
    },
    {
      "id": "yeast_ale_fermentis",
      "name": "SafAle US-05",
      "category": "yeast",
      "supplier": "Fermentis",
      "unit": "pack",
      "attenuation": "78-82%",
      "tempRange": "15-24°C",
      "flocculation": "medium",
      "yeastType": "ale"
    },
    {
      "id": "yeast_ale_s04_fermentis",
      "name": "SafAle S-04",
      "category": "yeast",
      "supplier": "Fermentis",
      "unit": "pack",
      "attenuation": "72-78%",
      "tempRange": "15-24°C",
      "flocculation": "high",
      "yeastType": "ale"
    },
    {
      "id": "yeast_ale_lallemand",
      "name": "LalBrew Nottingham",
      "category": "yeast",
      "supplier": "Lallemand",
      "unit": "pack",
      "attenuation": "77-82%",
      "tempRange": "10-22°C",
      "flocculation": "high",
      "yeastType": "ale"
    },
    {
      "id": "yeast_wheat_fermentis",
      "name": "SafAle WB-06",
      "category": "yeast",
      "supplier": "Fermentis",
      "unit": "pack",
      "attenuation": "86-90%",
      "tempRange": "18-24°C",
      "flocculation": "low",
      "yeastType": "wheat"
    },
    {
      "id": "yeast_belgian_fermentis",
      "name": "SafAle T-58",
      "category": "yeast",
      "supplier": "Fermentis",
      "unit": "pack",
      "attenuation": "72-78%",
      "tempRange": "15-24°C",
      "flocculation": "low",
      "yeastType": "belgian"
    },
    {
      "id": "yeast_belgian_be256_fermentis",
      "name": "SafAle BE-256",
      "category": "yeast",
      "supplier": "Fermentis",
      "unit": "pack",
      "attenuation": "82-86%",
      "tempRange": "15-24°C",
      "flocculation": "high",
      "yeastType": "belgian"
    },
    {
      "id": "yeast_pilsner_whitelabs",
      "name": "WLP800 Pilsner Lager",
      "category": "yeast",
      "supplier": "White Labs",
      "unit": "pack",
      "attenuation": "72-77%",
      "tempRange": "10-13°C",
      "flocculation": "medium",
      "yeastType": "lager"
    },
    {
      "id": "yeast_lager_whitelabs",
      "name": "WLP830 German Lager",
      "category": "yeast",
      "supplier": "White Labs",
      "unit": "pack",
      "attenuation": "74-79%",
      "tempRange": "10-13°C",
      "flocculation": "medium",
      "yeastType": "lager"
    },
    {
      "id": "yeast_ale_whitelabs",
      "name": "WLP001 California Ale",
      "category": "yeast",
      "supplier": "White Labs",
      "unit": "pack",
      "attenuation": "73-80%",
      "tempRange": "17-21°C",
      "flocculation": "medium",
      "yeastType": "ale"
    },
    {
      "id": "yeast_wheat_whitelabs",
      "name": "WLP300 Hefeweizen",
      "category": "yeast",
      "supplier": "White Labs",
      "unit": "pack",
      "attenuation": "72-76%",
      "tempRange": "18-22°C",
      "flocculation": "low",
      "yeastType": "wheat"
    },
    {
      "id": "yeast_belgian_whitelabs",
      "name": "WLP500 Trappist Ale",
      "category": "yeast",
      "supplier": "White Labs",
      "unit": "pack",
      "attenuation": "75-80%",
      "tempRange": "18-24°C",
      "flocculation": "medium",
      "yeastType": "belgian"
    },
    {
      "id": "yeast_ale_wyeast",
      "name": "Wyeast 1056 American Ale",
      "category": "yeast",
      "supplier": "Wyeast",
      "unit": "pack",
      "attenuation": "73-77%",
      "tempRange": "15-22°C",
      "flocculation": "medium",
      "yeastType": "ale"
    },
    {
      "id": "yeast_lager_wyeast",
      "name": "Wyeast 2124 Bohemian Lager",
      "category": "yeast",
      "supplier": "Wyeast",
      "unit": "pack",
      "attenuation": "69-73%",
      "tempRange": "9-14°C",
      "flocculation": "medium",
      "yeastType": "lager"
    },
    {
      "id": "yeast_belgian_wyeast",
      "name": "Wyeast 1214 Belgian Abbey",
      "category": "yeast",
      "supplier": "Wyeast",
      "unit": "pack",
      "attenuation": "74-78%",
      "tempRange": "17-23°C",
      "flocculation": "medium",
      "yeastType": "belgian"
    },
    {
      "id": "adjunct_gypsum",
      "name": "Gypsum (CaSO4)",
      "category": "adjunct",
      "supplier": "BrewChem",
      "unit": "kg",
      "description": "Adds calcium and sulfate ions",
      "adjunctType": "water_chemistry"
    },
    {
      "id": "adjunct_calcium_chloride",
      "name": "Calcium Chloride (CaCl2)",
      "category": "adjunct",
      "supplier": "BrewChem",
      "unit": "kg",
      "description": "Adds calcium and chloride ions",
      "adjunctType": "water_chemistry"
    },
    {
      "id": "adjunct_lactic_acid",
      "name": "Lactic Acid 80%",
      "category": "adjunct",
      "supplier": "BrewChem",
      "unit": "L",
      "description": "pH adjustment",
      "adjunctType": "water_chemistry"
    },
    {
      "id": "adjunct_phosphoric_acid",
      "name": "Phosphoric Acid 75%",
      "category": "adjunct",
      "supplier": "BrewChem",
      "unit": "L",
      "description": "pH adjustment",
      "adjunctType": "water_chemistry"
    },
    {
      "id": "adjunct_irish_moss",
      "name": "Irish Moss",
      "category": "adjunct",
      "supplier": "BrewChem",
      "unit": "kg",
      "description": "Kettle fining agent",
      "adjunctType": "fining"
    },
    {
      "id": "adjunct_whirlfloc",
      "name": "Whirlfloc Tablets",
      "category": "adjunct",
      "supplier": "Kerry",
      "unit": "pcs",
      "description": "Kettle fining agent",
      "adjunctType": "fining"
    },
    {
      "id": "adjunct_gelatin",
      "name": "Gelatin",
      "category": "adjunct",
      "supplier": "BrewChem",
      "unit": "kg",
      "description": "Cold-side fining agent",
      "adjunctType": "fining"
    },
    {
      "id": "adjunct_dextrose",
      "name": "Dextrose (Corn Sugar)",
      "category": "adjunct",
      "supplier": "BrewChem",
      "unit": "kg",
      "description": "Priming/fermentable sugar",
      "adjunctType": "sugar",
      "potential": 1.046
    },
    {
      "id": "adjunct_table_sugar",
      "name": "Table Sugar (Sucrose)",
      "category": "adjunct",
      "supplier": "Generic",
      "unit": "kg",
      "description": "Priming/fermentable sugar",
      "adjunctType": "sugar",
      "potential": 1.046
    },
    {
      "id": "adjunct_honey",
      "name": "Honey",
      "category": "adjunct",
      "supplier": "Local",
      "unit": "kg",
      "description": "Fermentable sugar with flavor",
      "adjunctType": "sugar",
      "potential": 1.035
    },
    {
      "id": "adjunct_coriander",
      "name": "Coriander Seeds",
      "category": "adjunct",
      "supplier": "Spice Trade",
      "unit": "kg",
      "description": "Spice for Witbier, Belgian styles",
      "adjunctType": "spice"
    },
    {
      "id": "adjunct_orange_peel",
      "name": "Orange Peel (Bitter)",
      "category": "adjunct",
      "supplier": "Spice Trade",
      "unit": "kg",
      "description": "Citrus flavor for Witbier, Belgian styles",
      "adjunctType": "spice"
    },
    {
      "id": "water_chem_campden",
      "name": "Campden Tablets (Sodium Metabisulfite)",
      "category": "water_chemistry",
      "supplier": "BrewChem",
      "unit": "pcs",
      "description": "Removes chlorine/chloramine from water"
    },
    {
      "id": "water_chem_baking_soda",
      "name": "Baking Soda (NaHCO3)",
      "category": "water_chemistry",
      "supplier": "BrewChem",
      "unit": "kg",
      "description": "Raises mash pH, adds sodium"
    },
    {
      "id": "water_chem_chalk",
      "name": "Chalk (CaCO3)",
      "category": "water_chemistry",
      "supplier": "BrewChem",
      "unit": "kg",
      "description": "Raises mash pH, adds calcium"
    },
    {
      "id": "water_chem_epsom_salt",
      "name": "Epsom Salt (MgSO4)",
      "category": "water_chemistry",
      "supplier": "BrewChem",
      "unit": "kg",
      "description": "Adds magnesium and sulfate"
    },
    {
      "id": "bestmalz_munich",
      "name": "BEST Munich Malt",
      "category": "malt",
      "supplier": "BestMalz",
      "unit": "kg",
      "color": 15,
      "colorRange": { "min": 11, "max": 20 },
      "potential": 1.037,
      "yield": 80.5,
      "maltType": "base",
      "origin": "Germany",
      "maxUsage": 100,
      "flavorNotes": ["malt", "bread", "honey"]
    },
    {
      "id": "bestmalz_munich_dark",
      "name": "BEST Munich Dark",
      "category": "malt",
      "supplier": "BestMalz",
      "unit": "kg",
      "color": 25,
      "colorRange": { "min": 21, "max": 30 },
      "potential": 1.037,
      "yield": 80.0,
      "maltType": "base",
      "origin": "Germany",
      "maxUsage": 100,
      "flavorNotes": ["bread", "honey"]
    },
    {
      "id": "bestmalz_caramel_hell",
      "name": "BEST Caramel Hell",
      "category": "malt",
      "supplier": "BestMalz",
      "unit": "kg",
      "color": 30,
      "colorRange": { "min": 20, "max": 40 },
      "potential": 1.035,
      "yield": 75.0,
      "maltType": "caramel",
      "origin": "Germany",
      "maxUsage": 30,
      "flavorNotes": ["honey", "caramel", "toffee"]
    },
    {
      "id": "bestmalz_caramel_aromatic",
      "name": "BEST Caramel Aromatic",
      "category": "malt",
      "supplier": "BestMalz",
      "unit": "kg",
      "color": 50,
      "colorRange": { "min": 41, "max": 60 },
      "potential": 1.035,
      "yield": 75.0,
      "maltType": "caramel",
      "origin": "Germany",
      "maxUsage": 25,
      "flavorNotes": ["caramel", "toffee", "biscuit", "almond"]
    },
    {
      "id": "bestmalz_chocolate",
      "name": "BEST Chocolate Malt",
      "category": "malt",
      "supplier": "BestMalz",
      "unit": "kg",
      "color": 900,
      "colorRange": { "min": 800, "max": 1000 },
      "potential": 1.035,
      "yield": 75.0,
      "maltType": "roasted",
      "origin": "Germany",
      "maxUsage": 10,
      "flavorNotes": ["chocolate"]
    },
    {
      "id": "bestmalz_black_malt",
      "name": "BEST Black Malt",
      "category": "malt",
      "supplier": "BestMalz",
      "unit": "kg",
      "color": 1150,
      "colorRange": { "min": 1100, "max": 1200 },
      "potential": 1.030,
      "yield": 65.0,
      "maltType": "roasted",
      "origin": "Germany",
      "maxUsage": 10,
      "flavorNotes": ["cacao", "coffee"]
    },
    {
      "id": "bestmalz_smoked",
      "name": "BEST Smoked Malt",
      "category": "malt",
      "supplier": "BestMalz",
      "unit": "kg",
      "color": 5,
      "colorRange": { "min": 3, "max": 8 },
      "potential": 1.035,
      "yield": 77.0,
      "maltType": "smoked",
      "origin": "Germany",
      "maxUsage": 100,
      "flavorNotes": ["smoke", "ham", "wood"]
    },
    {
      "id": "bestmalz_peated",
      "name": "BEST Peated Malt",
      "category": "malt",
      "supplier": "BestMalz",
      "unit": "kg",
      "color": 5,
      "colorRange": { "min": 3, "max": 8 },
      "potential": 1.036,
      "yield": 78.0,
      "maltType": "smoked",
      "origin": "Germany",
      "maxUsage": 100,
      "flavorNotes": ["peat", "smoke", "earthy"]
    },
    {
      "id": "bestmalz_wheat",
      "name": "BEST Wheat Malt",
      "category": "malt",
      "supplier": "BestMalz",
      "unit": "kg",
      "color": 4.5,
      "colorRange": { "min": 3.5, "max": 6 },
      "potential": 1.038,
      "yield": 82.0,
      "maltType": "base",
      "origin": "Germany",
      "maxUsage": 100,
      "flavorNotes": ["honey", "bread"]
    }
  ]
}
